spec2json/__init__.py
spec2json/cli.py
spec2json/exceptions.py
spec2json/numbering.py
spec2json/parsers/__init__.py
spec2json/parsers/base.py
spec2json/parsers/bikeshed.py
spec2json/parsers/ecmarkup.py
spec2json/parsers/wattsi.py
spec2json/spec.py
spec2json/utils.py
spec2json-0.1.0.dist-info/entry_points.txt
spec2json-0.1.0.dist-info/LICENSE
spec2json-0.1.0.dist-info/WHEEL
spec2json-0.1.0.dist-info/METADATA
spec2json-0.1.0.dist-info/RECORD
